<?xml version="1.0" encoding="utf-8"?>
<odoo>
    <data noupdate="1">
        <!--从库存取-->
        <!--<record id="app_stock_mts_else_mto.route_warehouse0_pull_mts" model='stock.location.route'>-->
            <!--<field name="sale_selectable" eval="True"/>-->
            <!--<field name="proc_plan_type">stock</field>-->
        <!--</record>-->
        <!--采购-->
        <record id="purchase_stock.route_warehouse0_buy" model='stock.location.route'>
            <field name="sale_selectable" eval="True"/>
            <field name="proc_plan_type">buy</field>
        </record>
        <!--制造-->
        <record id="mrp.route_warehouse0_manufacture" model='stock.location.route'>
            <field name="sale_selectable" eval="True"/>
            <field name="proc_plan_type">manufacture</field>
        </record>
    </data>
</odoo>
